uart.v
module uart_tx(
    input [7:0] data_bus,
    input byte_ready,
    input ld_tx_datareg,
    input t_byte,
    input clk,
    input reset_,
    output serial_out
);

    reg [7:0] tx_datareg;
    reg [8:0] tx_shiftreg;
    reg ld_tx_shiftreg;
    reg [2:0] state, next_state;
    reg [2:0] bit_count;
    reg clr;
    reg shift;
    reg start;

    parameter idle = 3'b001;
    parameter waiting = 3'b010;
    parameter sending = 3'b100;
    parameter all_ones = 9'b111111111;

    assign serial_out = tx_shiftreg[0]; //Output is LSB of shift register

    always @ (state or bit_count or t_byte or byte_ready)
    begin
        ld_tx_shiftreg = 0;
        clr = 0;
        shift = 0;
        start = 0;
        next_state = state;

        case(state)
            idle:
                if(byte_ready == 1)
                begin
                    ld_tx_shiftreg = 1;
                    next_state = waiting;
                end

            waiting:
                if(t_byte == 1)
                begin
                    start = 1;
                    next_state = sending;
                end

            sending:
                if(bit_count != 9)
                    shift = 1;
                else
                begin
                    clr = 1;
                    next_state = idle;
                end

            default: next_state = idle;
        endcase
    end

    always @ (posedge clk or negedge reset_)
    begin
        if(reset_ == 0)
            state <= idle;
        else
            state <= next_state;
    end

    always @ (posedge clk or negedge reset_)
    begin
        if(reset_ == 0)
        begin
            tx_shiftreg <= all_ones;
            bit_count <= 0; end
        else
        begin
            if(ld_tx_datareg == 1)
                tx_datareg <= data_bus;

            if(ld_tx_shiftreg == 1)
                tx_shiftreg <= {tx_datareg, 1'b1};

            if(start == 1)
                tx_shiftreg[0] <= 0;

            if(clr == 1)
                bit_count <= 0;

            else if(shift == 1)
                bit_count <= bit_count+1;

            if(shift == 1)
                tx_shiftreg <= {1'b1, tx_shiftreg[8:1]};
        end
    end
endmodule

module uart_rx(
    output reg [7:0] rx_datareg,
    output reg error1, error2,
    output rx_handshake, // read_not_ready_out
    input serial_in,
    input sample_clk,
    input reset_,
    input host_not_ready // read_not_ready_in
);

    parameter idle = 2'b00;
    parameter starting = 2'b01;
    parameter receiving = 2'b11;

    reg [7:0] rx_shiftreg;
    reg [3:0] sample_counter;
    reg [4:0] bit_counter;
    reg [1:0] state, next_state;

    reg inc_bit_counter, clr_bit_counter, inc_sample_counter, clr_sample_counter, shift, load, rx_handshake;

    always @(state or serial_in or host_not_ready or sample_counter or bit_counter)
    begin
        rx_handshake = 0;
        clr_sample_counter = 0;
        clr_bit_counter = 0;
        inc_sample_counter = 0;
        inc_bit_counter = 0;
        shift = 0;
        error1 = 0;
        error2 = 0;
        load = 0;
        next_state = state;

        case (state)
            idle: if(serial_in == 0) next_state = starting;

            starting:
                begin
                    if(serial_in == 1)
                    begin
                        next_state = idle;
                        clr_sample_counter = 1;
                    end
                    else if(sample_counter == 3) // Check if sample_counter == half_word - 1 (half_word = word_size/2 = 8/2 = 4) = 3
                    begin
                        next_state = receiving;
                        clr_sample_counter = 1;
                    end
                    else inc_sample_counter = 1;
                end
            receiving:
                begin
                    if(sample_counter < 7) // word_size - 1
                    begin
                        inc_sample_counter = 1;
                    end
                    else
                    begin
                       clr_sample_counter = 1;
                       if(bit_counter != 8)
                       begin
                           shift = 1;
                           inc_bit_counter = 1;
                       end
                       else
                       begin
                           next_state = idle;
                           rx_handshake = 1;
                           clr_bit_counter = 1;
                           if(host_not_ready == 1)
                                error1 = 1;
                           else if(serial_in == 0)
                                error2 = 1;
                           else
                               load = 1;
                       end
                    end
                end
            default: next_state = idle;
        endcase
    end

    // State transitions and register transfers

    always @ (posedge sample_clk)
    begin
        if(reset_ == 0)
        begin
            state <= idle;
            sample_counter <= 0;
            bit_counter <= 0;
            rx_datareg <= 0;
            rx_shiftreg <= 0;
        end

        else begin
            state <= next_state;

            if(clr_sample_counter == 1)
                sample_counter <= 0;
            else if(inc_sample_counter == 1)
                sample_counter <= sample_counter + 1;

            if(clr_bit_counter == 1)
                bit_counter <= 0;
            else if(inc_bit_counter == 1)
                bit_counter <= bit_counter + 1;

            if(shift == 1)
                rx_shiftreg <= {serial_in, rx_shiftreg[7:1]};
            if(load == 1)
                rx_datareg <= rx_shiftreg;
        end
    end
endmodule

tb_uart.v
`timescale 1ns/1ps
module tb_uart_rx();
    // Common
    reg reset_;

    // for Rx
    wire [7:0] rx_datareg;
    wire error1, error2;
    wire rx_handshake; //read_not_ready_out
    reg sample_clk;
    reg host_not_ready; // read_not_ready_in

    // for Tx
    reg [7:0] data_bus;
    reg t_byte;
    reg ld_tx_datareg;
    reg clk;
    reg byte_ready;
    wire serial_out;

    uart_tx TX(
        .data_bus(data_bus),
        .byte_ready(byte_ready),
        .ld_tx_datareg(ld_tx_datareg),
        .clk(clk), .reset_(reset_),
        .serial_out(serial_out),
        .t_byte(t_byte)
    );

    uart_rx RX(
        .rx_datareg(rx_datareg),
        .error1(error1),
        .error2(error2),
        .rx_handshake(rx_handshake),
        .serial_in(serial_out),
        .sample_clk(sample_clk),
        .reset_(reset_),
        .host_not_ready(host_not_ready)
    );

    // Clock at Tx
    initial
    begin
        clk = 1'b0;
    end
    always
    begin
        #5 clk = ~clk;
    end

    // Clock at Rx
    // The frequency is 8 times that of the Tx to sample effectively
    initial
    begin
        sample_clk = 1'b0;
    end
    always
    begin
        #0.625 sample_clk = ~sample_clk;
    end

    initial
    begin
        $dumpfile("uart_rx.vcd");
        $dumpvars(0, tb_uart_rx);
    end

    initial
    begin
        $monitor($time, " Serial input = %x | Clock = %x | Reset = %x | Output = %x", data_bus, sample_clk, reset_, rx_datareg);
    end

    initial
    begin
        #1 reset_ = 1'b0;
        #3 reset_ = 1'b1;
        host_not_ready = 1'b0;

        // Set up Tx, and start sending
        data_bus = 8'haa;
        ld_tx_datareg = 1'b1;
        #10 byte_ready = 1'b1;
        #10 t_byte = 1'b1;

        #200 $finish;
    end
endmodule

tb_uart.vcd
$date
	Tue Apr 27 17:33:09 2021
$end
$version
	Icarus Verilog
$end
$timescale
	1ps
$end
$scope module tb_uart_rx $end
$var wire 1 ! serial_out $end
$var wire 1 " rx_handshake $end
$var wire 8 # rx_datareg [7:0] $end
$var wire 1 $ error2 $end
$var wire 1 % error1 $end
$var reg 1 & byte_ready $end
$var reg 1 ' clk $end
$var reg 8 ( data_bus [7:0] $end
$var reg 1 ) host_not_ready $end
$var reg 1 * ld_tx_datareg $end
$var reg 1 + reset_ $end
$var reg 1 , sample_clk $end
$var reg 1 - t_byte $end
$scope module RX $end
$var wire 1 ) host_not_ready $end
$var wire 1 + reset_ $end
$var wire 1 , sample_clk $end
$var wire 1 ! serial_in $end
$var reg 5 . bit_counter [4:0] $end
$var reg 1 / clr_bit_counter $end
$var reg 1 0 clr_sample_counter $end
$var reg 1 % error1 $end
$var reg 1 $ error2 $end
$var reg 1 1 inc_bit_counter $end
$var reg 1 2 inc_sample_counter $end
$var reg 1 3 load $end
$var reg 2 4 next_state [1:0] $end
$var reg 8 5 rx_datareg [7:0] $end
$var reg 1 " rx_handshake $end
$var reg 8 6 rx_shiftreg [7:0] $end
$var reg 4 7 sample_counter [3:0] $end
$var reg 1 8 shift $end
$var reg 2 9 state [1:0] $end
$upscope $end
$scope module TX $end
$var wire 1 & byte_ready $end
$var wire 1 ' clk $end
$var wire 8 : data_bus [7:0] $end
$var wire 1 * ld_tx_datareg $end
$var wire 1 + reset_ $end
$var wire 1 - t_byte $end
$var wire 1 ! serial_out $end
$var reg 3 ; bit_count [2:0] $end
$var reg 1 < clr $end
$var reg 1 = ld_tx_shiftreg $end
$var reg 3 > next_state [2:0] $end
$var reg 1 ? shift $end
$var reg 1 @ start $end
$var reg 3 A state [2:0] $end
$var reg 8 B tx_datareg [7:0] $end
$var reg 9 C tx_shiftreg [8:0] $end
$upscope $end
$upscope $end
$enddefinitions $end
#0
$dumpvars
bx C
bx B
bx A
x@
x?
bx >
x=
x<
bx ;
bx :
bx 9
x8
bx 7
bx 6
bx 5
bx 4
x3
x2
x1
x0
x/
bx .
x-
0,
x+
x*
x)
bx (
0'
x&
x%
x$
bx #
x"
x!
$end
#625
1,
#1000
b0 4
03
0$
0%
08
01
02
0/
00
0"
b1 >
0@
0?
0<
0=
1!
b1 A
b0 ;
b111111111 C
0+
#1250
0,
#1875
b0 6
b0 #
b0 5
b0 .
b0 7
b0 9
1,
#2500
0,
#3125
1,
#3750
0,
#4000
1*
b10101010 (
b10101010 :
0)
1+
#4375
1,
#5000
b10101010 B
0,
1'
#5625
1,
#6250
0,
#6875
1,
#7500
0,
#8125
1,
#8750
0,
#9375
1,
#10000
0,
0'
#10625
1,
#11250
0,
#11875
1,
#12500
0,
#13125
1,
#13750
0,
#14000
b10 >
1=
1&
#14375
1,
#15000
0=
b10 A
b101010101 C
0,
1'
#15625
1,
#16250
0,
#16875
1,
#17500
0,
#18125
1,
#18750
0,
#19375
1,
#20000
0,
0'
#20625
1,
#21250
0,
#21875
1,
#22500
0,
#23125
1,
#23750
0,
#24000
b100 >
1@
1-
#24375
1,
#25000
b1 4
0!
1?
0@
b101010100 C
b100 A
0,
1'
#25625
12
b1 9
1,
#26250
0,
#26875
12
b1 7
1,
#27500
0,
#28125
12
b10 7
1,
#28750
0,
#29375
10
b11 4
02
b11 7
1,
#30000
0,
0'
#30625
12
00
b0 7
b11 9
1,
#31250
0,
#31875
12
b1 7
1,
#32500
0,
#33125
12
b10 7
1,
#33750
0,
#34375
12
b11 7
1,
#35000
1?
b110101010 C
b1 ;
0,
1'
#35625
12
b100 7
1,
#36250
0,
#36875
12
b101 7
1,
#37500
0,
#38125
12
b110 7
1,
#38750
0,
#39375
11
18
10
02
b111 7
1,
#40000
0,
0'
#40625
12
08
01
00
b1 .
b0 7
1,
#41250
0,
#41875
12
b1 7
1,
#42500
0,
#43125
12
b10 7
1,
#43750
0,
#44375
12
b11 7
1,
#45000
12
1!
1?
b111010101 C
b10 ;
0,
1'
#45625
12
b100 7
1,
#46250
0,
#46875
12
b101 7
1,
#47500
0,
#48125
12
b110 7
1,
#48750
0,
#49375
11
18
10
02
b111 7
1,
#50000
0,
0'
#50625
12
08
01
00
b10000000 6
b10 .
b0 7
1,
#51250
0,
#51875
12
b1 7
1,
#52500
0,
#53125
12
b10 7
1,
#53750
0,
#54375
12
b11 7
1,
#55000
12
0!
1?
b111101010 C
b11 ;
0,
1'
#55625
12
b100 7
1,
#56250
0,
#56875
12
b101 7
1,
#57500
0,
#58125
12
b110 7
1,
#58750
0,
#59375
11
18
10
02
b111 7
1,
#60000
0,
0'
#60625
12
08
01
00
b1000000 6
b11 .
b0 7
1,
#61250
0,
#61875
12
b1 7
1,
#62500
0,
#63125
12
b10 7
1,
#63750
0,
#64375
12
b11 7
1,
#65000
12
1!
1?
b111110101 C
b100 ;
0,
1'
#65625
12
b100 7
1,
#66250
0,
#66875
12
b101 7
1,
#67500
0,
#68125
12
b110 7
1,
#68750
0,
#69375
11
18
10
02
b111 7
1,
#70000
0,
0'
#70625
12
08
01
00
b10100000 6
b100 .
b0 7
1,
#71250
0,
#71875
12
b1 7
1,
#72500
0,
#73125
12
b10 7
1,
#73750
0,
#74375
12
b11 7
1,
#75000
12
0!
1?
b111111010 C
b101 ;
0,
1'
#75625
12
b100 7
1,
#76250
0,
#76875
12
b101 7
1,
#77500
0,
#78125
12
b110 7
1,
#78750
0,
#79375
11
18
10
02
b111 7
1,
#80000
0,
0'
#80625
12
08
01
00
b1010000 6
b101 .
b0 7
1,
#81250
0,
#81875
12
b1 7
1,
#82500
0,
#83125
12
b10 7
1,
#83750
0,
#84375
12
b11 7
1,
#85000
12
1!
1?
b111111101 C
b110 ;
0,
1'
#85625
12
b100 7
1,
#86250
0,
#86875
12
b101 7
1,
#87500
0,
#88125
12
b110 7
1,
#88750
0,
#89375
11
18
10
02
b111 7
1,
#90000
0,
0'
#90625
12
08
01
00
b10101000 6
b110 .
b0 7
1,
#91250
0,
#91875
12
b1 7
1,
#92500
0,
#93125
12
b10 7
1,
#93750
0,
#94375
12
b11 7
1,
#95000
12
0!
1?
b111111110 C
b111 ;
0,
1'
#95625
12
b100 7
1,
#96250
0,
#96875
12
b101 7
1,
#97500
0,
#98125
12
b110 7
1,
#98750
0,
#99375
11
18
10
02
b111 7
1,
#100000
0,
0'
#100625
12
08
01
00
b1010100 6
b111 .
b0 7
1,
#101250
0,
#101875
12
b1 7
1,
#102500
0,
#103125
12
b10 7
1,
#103750
0,
#104375
12
b11 7
1,
#105000
12
1!
1?
b111111111 C
b0 ;
0,
1'
#105625
12
b100 7
1,
#106250
0,
#106875
12
b101 7
1,
#107500
0,
#108125
12
b110 7
1,
#108750
0,
#109375
11
18
10
02
b111 7
1,
#110000
0,
0'
#110625
12
08
01
00
b10101010 6
b1000 .
b0 7
1,
#111250
0,
#111875
12
b1 7
1,
#112500
0,
#113125
12
b10 7
1,
#113750
0,
#114375
12
b11 7
1,
#115000
1?
b1 ;
0,
1'
#115625
12
b100 7
1,
#116250
0,
#116875
12
b101 7
1,
#117500
0,
#118125
12
b110 7
1,
#118750
0,
#119375
13
1/
1"
b0 4
10
02
b111 7
1,
#120000
0,
0'
#120625
03
0/
00
0"
b10101010 #
b10101010 5
b0 .
b0 7
b0 9
1,
#121250
0,
#121875
1,
#122500
0,
#123125
1,
#123750
0,
#124375
1,
#125000
1?
b10 ;
0,
1'
#125625
1,
#126250
0,
#126875
1,
#127500
0,
#128125
1,
#128750
0,
#129375
1,
#130000
0,
0'
#130625
1,
#131250
0,
#131875
1,
#132500
0,
#133125
1,
#133750
0,
#134375
1,
#135000
1?
b11 ;
0,
1'
#135625
1,
#136250
0,
#136875
1,
#137500
0,
#138125
1,
#138750
0,
#139375
1,
#140000
0,
0'
#140625
1,
#141250
0,
#141875
1,
#142500
0,
#143125
1,
#143750
0,
#144375
1,
#145000
1?
b100 ;
0,
1'
#145625
1,
#146250
0,
#146875
1,
#147500
0,
#148125
1,
#148750
0,
#149375
1,
#150000
0,
0'
#150625
1,
#151250
0,
#151875
1,
#152500
0,
#153125
1,
#153750
0,
#154375
1,
#155000
1?
b101 ;
0,
1'
#155625
1,
#156250
0,
#156875
1,
#157500
0,
#158125
1,
#158750
0,
#159375
1,
#160000
0,
0'
#160625
1,
#161250
0,
#161875
1,
#162500
0,
#163125
1,
#163750
0,
#164375
1,
#165000
1?
b110 ;
0,
1'
#165625
1,
#166250
0,
#166875
1,
#167500
0,
#168125
1,
#168750
0,
#169375
1,
#170000
0,
0'
#170625
1,
#171250
0,
#171875
1,
#172500
0,
#173125
1,
#173750
0,
#174375
1,
#175000
1?
b111 ;
0,
1'
#175625
1,
#176250
0,
#176875
1,
#177500
0,
#178125
1,
#178750
0,
#179375
1,
#180000
0,
0'
#180625
1,
#181250
0,
#181875
1,
#182500
0,
#183125
1,
#183750
0,
#184375
1,
#185000
1?
b0 ;
0,
1'
#185625
1,
#186250
0,
#186875
1,
#187500
0,
#188125
1,
#188750
0,
#189375
1,
#190000
0,
0'
#190625
1,
#191250
0,
#191875
1,
#192500
0,
#193125
1,
#193750
0,
#194375
1,
#195000
1?
b1 ;
0,
1'
#195625
1,
#196250
0,
#196875
1,
#197500
0,
#198125
1,
#198750
0,
#199375
1,
#200000
0,
0'
#200625
1,
#201250
0,
#201875
1,
#202500
0,
#203125
1,
#203750
0,
#204375
1,
#205000
1?
b10 ;
0,
1'
#205625
1,
#206250
0,
#206875
1,
#207500
0,
#208125
1,
#208750
0,
#209375
1,
#210000
0,
0'
#210625
1,
#211250
0,
#211875
1,
#212500
0,
#213125
1,
#213750
0,
#214375
1,
#215000
1?
b11 ;
0,
1'
